bicleaner_ai/__init__.py
bicleaner_ai/bicleaner_ai_classifier.py
bicleaner_ai/bicleaner_ai_download.py
bicleaner_ai/bicleaner_ai_download_hf.py
bicleaner_ai/bicleaner_ai_generate_train.py
bicleaner_ai/bicleaner_ai_sample.py
bicleaner_ai/bicleaner_ai_train.py
bicleaner_ai/calibrate.py
bicleaner_ai/classify.py
bicleaner_ai/datagen.py
bicleaner_ai/decomposable_attention.py
bicleaner_ai/layers.py
bicleaner_ai/losses.py
bicleaner_ai/metrics.py
bicleaner_ai/models.py
bicleaner_ai/models_util.py
bicleaner_ai/noise_generation.py
bicleaner_ai/tokenizer.py
bicleaner_ai/training.py
bicleaner_ai/util.py
bicleaner_ai/word_freqs_list.py
bicleaner_ai/word_freqs_zipf.py
bicleaner_ai/word_freqs_zipf_double_linked.py
bicleaner_ai-3.4.dist-info/licenses/LICENSE
bicleaner_ai-3.4.dist-info/METADATA
bicleaner_ai-3.4.dist-info/WHEEL
bicleaner_ai-3.4.dist-info/entry_points.txt
bicleaner_ai-3.4.dist-info/top_level.txt
bicleaner_ai-3.4.dist-info/RECORD
