Metadata-Version: 2.4
Name: bicleaner-ai
Version: 3.4
Summary: Parallel corpus classifier, indicating the likelihood of a pair of sentences being mutual translations or not (neural version)
Author-email: Prompsit Language Engineering <info@prompsit.com>
Maintainer-email: Jaume Zaragoza <jzaragoza@prompsit.com>
License:                     GNU GENERAL PUBLIC LICENSE
Classifier: Environment :: Console
Classifier: Intended Audience :: Science/Research
Classifier: Programming Language :: Python :: 3.7
Classifier: License :: OSI Approved :: GNU General Public License v3 (GPLv3)
Classifier: Operating System :: POSIX :: Linux
Classifier: Topic :: Scientific/Engineering :: Artificial Intelligence
Classifier: Topic :: Text Processing :: Linguistic
Classifier: Topic :: Software Development :: Libraries :: Python Modules
Classifier: Topic :: Text Processing :: Filters
Requires-Python: >=3.8
License-File: LICENSE
Requires-Dist: scikit-learn>=0.22.1
Requires-Dist: PyYAML>=5.1.2
Requires-Dist: numpy<2
Requires-Dist: pytest
Requires-Dist: toolwrapper
Requires-Dist: sentencepiece
Requires-Dist: protobuf==3.20.3
Requires-Dist: tensorflow<2.16,>=2.6.5
Requires-Dist: bicleaner-ai-glove==0.2.1
Requires-Dist: transformers==4.52.4
Requires-Dist: huggingface-hub<1,>=0.30
Requires-Dist: regex
Provides-Extra: transliterate
Requires-Dist: cyrtranslit==1.1; extra == "transliterate"
Provides-Extra: hardrules
Requires-Dist: bicleaner-hardrules==2.10.8; extra == "hardrules"
Provides-Extra: train
Requires-Dist: sacremoses; extra == "train"
Requires-Dist: fuzzywuzzy; extra == "train"
Requires-Dist: python-Levenshtein; extra == "train"
Requires-Dist: zstandard; extra == "train"
Provides-Extra: all
Requires-Dist: bicleaner-ai[hardrules,train,transliterate]; extra == "all"
Dynamic: license-file
